object_pool/__init__.py
object_pool/exception.py
object_pool/pool.py
object_pool/singleton_meta.py
object_pool/tests/__init__.py
object_pool/tests/browser_test.py
object_pool/tests/cls.py
object_pool/tests/test_browser_pool_behaviour.py
object_pool/tests/test_pool_behaviour.py
object_pool/tests/test_pool_creation.py
object_pool/tests/test_pool_functions.py
py_object_pool-1.1.dist-info/LICENSE
py_object_pool-1.1.dist-info/METADATA
py_object_pool-1.1.dist-info/WHEEL
py_object_pool-1.1.dist-info/top_level.txt
py_object_pool-1.1.dist-info/RECORD
