Metadata-Version: 2.1
Name: py-object-pool
Version: 1.1
Summary: Object pool creation library
Home-page: https://github.com/dduraipandian/object_pool
Author: Durai Pandian
Author-email: dduraipandian@gmail.com
License: UNKNOWN
Keywords: Object pool creation library
Platform: UNKNOWN
Classifier: Programming Language :: Python
Classifier: License :: OSI Approved :: MIT License
Classifier: Natural Language :: English
Classifier: Intended Audience :: Developers
Classifier: Operating System :: OS Independent
Requires-Python: >=3.6
